flet_web/__init__.py
flet_web/fastapi/README.md
flet_web/fastapi/__init__.py
flet_web/fastapi/app.py
flet_web/fastapi/flet_app.py
flet_web/fastapi/flet_app_manager.py
flet_web/fastapi/flet_fastapi.py
flet_web/fastapi/flet_oauth.py
flet_web/fastapi/flet_static_files.py
flet_web/fastapi/flet_upload.py
flet_web/fastapi/oauth_state.py
flet_web/fastapi/serve_fastapi_web_app.py
flet_web/patch_index.py
flet_web/uploads.py
flet_web/version.py
flet_contrive_web-2025.3.19.1311.dist-info/METADATA
flet_contrive_web-2025.3.19.1311.dist-info/WHEEL
flet_contrive_web-2025.3.19.1311.dist-info/RECORD
