Metadata-Version: 2.3
Name: flet-contrive-web
Version: 2025.3.19.1311
Summary: Flet web client in Flutter.
License: Apache-2.0
Author: Appveyor Systems Inc.
Author-email: hello@flet.dev
Requires-Python: >=3.8,<4.0
Classifier: License :: OSI Approved :: Apache Software License
Classifier: Programming Language :: Python :: 3
Classifier: Programming Language :: Python :: 3.8
Classifier: Programming Language :: Python :: 3.9
Classifier: Programming Language :: Python :: 3.10
Classifier: Programming Language :: Python :: 3.11
Classifier: Programming Language :: Python :: 3.12
Classifier: Programming Language :: Python :: 3.13
Requires-Dist: fastapi
Requires-Dist: flet_contributive (==2025.03.19.1311)
Requires-Dist: uvicorn[standard]
Project-URL: documentation, https://flet.dev/docs
Project-URL: homepage, https://flet.dev
Project-URL: repository, https://github.com/flet-dev/flet
